mooshak/__init__.py
mooshak/app.py
mooshak/app.tcss
mooshak/screens/__init__.py
mooshak/screens/home.py
mooshak-0.0.1.dist-info/METADATA
mooshak-0.0.1.dist-info/WHEEL
mooshak-0.0.1.dist-info/entry_points.txt
mooshak-0.0.1.dist-info/licenses/LICENSE
mooshak-0.0.1.dist-info/RECORD
